openyolos/OpenYolos.py
openyolos/__init__.py
openyolos/models/__init__.py
openyolos/models/activations.py
openyolos/models/common.py
openyolos/models/datasets.py
openyolos/models/experimental.py
openyolos/models/export.py
openyolos/models/general.py
openyolos/models/google_utils.py
openyolos/models/torch_utils.py
openyolos/models/yolo.py
open_yolo-0.1.4.dist-info/METADATA
open_yolo-0.1.4.dist-info/WHEEL
open_yolo-0.1.4.dist-info/top_level.txt
open_yolo-0.1.4.dist-info/zip-safe
open_yolo-0.1.4.dist-info/RECORD
